kontur/checkgrammar/__init__.py
kontur/checkgrammar/cli.py
kontur/checkgrammar/grammar.py
kontur/checkgrammar/parse.py
onec_checkgrammar-0.5.4.dist-info/LICENSE
onec_checkgrammar-0.5.4.dist-info/METADATA
onec_checkgrammar-0.5.4.dist-info/WHEEL
onec_checkgrammar-0.5.4.dist-info/entry_points.txt
onec_checkgrammar-0.5.4.dist-info/top_level.txt
onec_checkgrammar-0.5.4.dist-info/RECORD
