Metadata-Version: 2.1
Name: onec-checkgrammar
Version: 0.5.4
Summary: Проверка орфографии элементов формы для 1с
Home-page: https://github.com/kontur-1c/onec-grammarcheck
Author: a.krapivin
Author-email: krapivin_andrey@mail.ru
Maintainer: a.krapivin
Maintainer-email: krapivin_andrey@mail.ru
Classifier: Programming Language :: Python :: 3.6
Classifier: Programming Language :: Python :: 3.7
Classifier: Programming Language :: Python :: 3.8
Classifier: Programming Language :: Python :: 3.9
Classifier: Programming Language :: Python :: 3.10
Classifier: Operating System :: OS Independent
Requires-Python: >=3.6
License-File: LICENSE
Requires-Dist: pyaspeller ==2.0.0
Requires-Dist: Click
Requires-Dist: junit-xml ==1.8
Requires-Dist: wasabi
Requires-Dist: tqdm
Requires-Dist: typing-extensions
